README.rst
setup.py
data_files/CustomSecurityPolicy.py
data_files/moin.wsgi
data_files/wikiconfig.py
modoco/__init__.py
modoco/monkey.py
modoco.egg-info/PKG-INFO
modoco.egg-info/SOURCES.txt
modoco.egg-info/dependency_links.txt
modoco.egg-info/requires.txt
modoco.egg-info/top_level.txt
modoco/deploy/__init__.py
modoco/deploy/deploy.py
modoco/deploy/util.py
modoco/deploy/moin_package/CategorySOP.raw
modoco/deploy/moin_package/CreateAccount.raw
modoco/deploy/moin_package/FrontPage.raw
modoco/deploy/moin_package/HelpOnModoco.attachment1
modoco/deploy/moin_package/HelpOnModoco.raw
modoco/deploy/moin_package/HelpOnPublishPage.raw
modoco/deploy/moin_package/History.py
modoco/deploy/moin_package/MOIN_PACKAGE
modoco/deploy/moin_package/PublishPage.py
modoco/deploy/moin_package/PublisherGroup.raw
modoco/deploy/moin_package/README
modoco/deploy/moin_package/SOPTemplate.raw
modoco/deploy/moin_package/draft-not-sop.png
modoco/deploy/moin_package/modoco-custom.css
modoco/deploy/moin_package/modoco-logo.png
modoco/deploy/moin_package/newaccount.py