Metadata-Version: 1.1
Name: modoco
Version: 1.3.0
Summary: MoinMoin wiki configured as document control
Home-page: https://genomeinfo.qimrberghofer.edu.au/svn/genomeinfo/production/modoco
Author: Conrad Leonard
Author-email: Conrad.Leonard@qimrberghofer.edu.au
License: GPLv2
Platform: UNKNOWN
Classifier: Development Status :: 4 - Beta
Classifier: Environment :: Web Environment
Classifier: Intended Audience :: End Users/Desktop
Classifier: License :: OSI Approved :: GNU General Public License v2 (GPLv2)
Classifier: Operating System :: MacOS :: MacOS X
Classifier: Operating System :: Microsoft :: Windows
Classifier: Operating System :: POSIX
Classifier: Programming Language :: Python
Classifier: Topic :: Documentation
Classifier: Topic :: Office/Business :: Groupware
Classifier: Topic :: Internet :: WWW/HTTP :: Dynamic Content :: Wiki
